setup.py
bbbok/__init__.py
bbbok.egg-info/PKG-INFO
bbbok.egg-info/SOURCES.txt
bbbok.egg-info/dependency_links.txt
bbbok.egg-info/top_level.txt