Metadata-Version: 1.1
Name: bbbok
Version: 0.4.0
Summary: Testing OS Dependency vuln
Home-page: UNKNOWN
Author: ..
Author-email: UNKNOWN
License: UNKNOWN
Platform: UNKNOWN
Classifier: Development Status :: 3 - Alpha
Classifier: Programming Language :: Python :: 3
